[
  { "composer": "Brahms", "work": "Violin Concerto" },
  { "composer": "Mendelssohn", "work": "Violin Concerto" },
  { "composer": "Dvořák", "work": "Cello Concerto" },
  { "composer": "Bach", "work": "Double Violin Concerto (BWV 1043)" },
  { "composer": "Sibelius", "work": "Violin Concerto" },
  { "composer": "Bruch", "work": "Violin Concerto No. 1" },
  { "composer": "Vivaldi", "work": "The Four Seasons" },
  { "composer": "Beethoven", "work": "Violin Concerto" },
  { "composer": "Berg", "work": "Violin Concerto" },
  { "composer": "Elgar", "work": "Cello Concerto" },
  { "composer": "Tchaikovsky", "work": "Violin Concerto" },
  { "composer": "Mozart", "work": "Violin Concerto No. 5 'Turkish'" },
  { "composer": "Prokofiev", "work": "Violin Concerto No. 1" },
  { "composer": "Brahms", "work": "Double Concerto" },
  { "composer": "Bartók", "work": "Violin Concerto No. 2" },
  { "composer": "Bach", "work": "Violin Concerto No. 1 (BWV 1041)" },
  { "composer": "Mozart", "work": "Sinfonia Concertante" },
  { "composer": "Barber", "work": "Violin Concerto" },
  { "composer": "Shostakovich", "work": "Violin Concerto No. 1" },
  { "composer": "Bach", "work": "Violin Concerto No. 2 (BWV 1042)" },
  { "composer": "Schumann", "work": "Cello Concerto" },
  { "composer": "Lalo", "work": "Symphonie Espagnole" },
  { "composer": "Haydn", "work": "Cello Concerto No. 1" },
  { "composer": "Dvořák", "work": "Violin Concerto" },
  { "composer": "Mozart", "work": "Violin Concerto No. 4" },
  { "composer": "Saint-Saëns", "work": "Cello Concerto No. 1" },
  { "composer": "Korngold", "work": "Violin Concerto" },
  { "composer": "Glazunov", "work": "Violin Concerto" },
  { "composer": "Prokofiev", "work": "Violin Concerto No. 2" },
  { "composer": "Haydn", "work": "Cello Concerto No. 2" },
  { "composer": "Vaughan Williams", "work": "The Lark Ascending" },
  { "composer": "Schumann", "work": "Violin Concerto" },
  { "composer": "Mozart", "work": "Violin Concerto No. 3" },
  { "composer": "Prokofiev", "work": "Symphony-Concerto" },
  { "composer": "Paganini", "work": "Violin Concerto No. 1" },
  { "composer": "Saint-Saëns", "work": "Violin Concerto No. 3" },
  { "composer": "Saint-Saëns", "work": "Introduction and Rondo Capriccioso" },
  { "composer": "Shostakovich", "work": "Cello Concerto No. 1" },
  { "composer": "Tchaikovsky", "work": "Variations on a Rococo Theme" },
  { "composer": "Bartók", "work": "Violin Concerto No. 1" },
  { "composer": "Khachaturian", "work": "Violin Concerto" },
  { "composer": "Beethoven", "work": "Violin Romance No. 1" },
  { "composer": "Chausson", "work": "Poème for Violin and Orchestra" },
  { "composer": "Ravel", "work": "Tzigane" },
  { "composer": "Walton", "work": "Viola Concerto" },
  { "composer": "Vivaldi", "work": "L'estro Armonico" },
  { "composer": "Elgar", "work": "Violin Concerto" },
  { "composer": "Schoenberg", "work": "Violin Concerto" },
  { "composer": "Beethoven", "work": "Violin Romance No. 2" },
  { "composer": "Bruch", "work": "Kol Nidrei" }
]